pytest_polarion_collect/__init__.py
pytest_polarion_collect/collector_hooks.py
pytest_polarion_collect/hookspec.py
pytest_polarion_collect/polarion_collect.py
pytest_polarion_collect/utils.py
pytest_polarion_collect-0.25.0.dist-info/METADATA
pytest_polarion_collect-0.25.0.dist-info/WHEEL
pytest_polarion_collect-0.25.0.dist-info/entry_points.txt
pytest_polarion_collect-0.25.0.dist-info/top_level.txt
pytest_polarion_collect-0.25.0.dist-info/RECORD
